indipyterm/__init__.py
indipyterm/__main__.py
indipyterm/devicesc.py
indipyterm/filechooser.py
indipyterm/iclient.py
indipyterm/iterm.py
indipyterm/memberpn.py
indipyterm/vectorpn.py
indipyterm-0.1.5.dist-info/entry_points.txt
indipyterm-0.1.5.dist-info/licenses/LICENSE
indipyterm-0.1.5.dist-info/WHEEL
indipyterm-0.1.5.dist-info/METADATA
indipyterm-0.1.5.dist-info/RECORD
