Metadata-Version: 2.4
Name: indipyterm
Version: 0.1.5
Summary: A terminal client which can be used to control remote instruments using the INDI protocol.
Keywords: indi,client,astronomy,instrument
Author-email: Bernard Czenkusz <bernie@skipole.co.uk>
Requires-Python: >=3.10
Classifier: License :: OSI Approved :: MIT License
Classifier: Topic :: Scientific/Engineering :: Astronomy
Classifier: Topic :: Scientific/Engineering :: Interface Engine/Protocol Translator
License-File: LICENSE
Requires-Dist: indipyclient>=0.8.6
Requires-Dist: textual>=3.6.0
Project-URL: Source, https://github.com/bernie-skipole/indipyterm
